dnts/__init__.py
dnts/parse.py
dnts-0.0.3.dist-info/LICENSE
dnts-0.0.3.dist-info/METADATA
dnts-0.0.3.dist-info/WHEEL
dnts-0.0.3.dist-info/top_level.txt
dnts-0.0.3.dist-info/RECORD
