Metadata-Version: 2.1
Name: dnts
Version: 0.0.3
Summary: Domain Names, Tools & Stuff
Home-page: https://github.com/neilodonuts/dnts
Author: Neil C. Obremski
Author-email: neilo@donuts.email
License: UNKNOWN
Platform: UNKNOWN
Classifier: Programming Language :: Python :: 3
Classifier: License :: OSI Approved :: MIT License
Classifier: Operating System :: OS Independent
Requires-Python: >=3.6
